{
    "cat": {
        "description": "gain 0.2% from talking instead of 0.1%",
        "max-hunger": 75,
        "cost": ["5","2%"],
        "favorite-food": "fish"
    },
    "tiger": {
        "description": "get taxed -0.3% - 0.6% instead of 0.1% - 0.8%",
        "max-hunger": 85,
        "cost": ["5", "3%"],
        "favorite-food": "meat"
    },
    "puffle": {
        "description": "every 60 seconds, there is a 5% chance to dig up a treasure",
        "max-hunger": 60,
        "cost": ["10", "4%"],
        "favorite-food": "bone"
    },
    "dog": {
        "description": "start with 110 hp in battle instead of 100",
        "max-hunger": 100,
        "cost": ["1.5%", "2"],
        "favorite-food": "bone"
    },
    "bird": {
        "description": "Last run is worth twice as much",
        "max-hunger": 40,
        "cost": ["3"],
        "favorite-food": "worm"
    },
    "frog": {
        "description": "When you are taxed, the frog takes 0.1% from everyone above you",
        "max-hunger": 50,
        "cost": ["1%"],
        "favorite-food": "fly"
    },
    "shark": {
        "description": "There is a 20% chance to find loot at the bottom of the ocean when fishing",
        "max-hunger": 80,
        "cost": ["3", "4%"],
        "favorite-food": "seal"
    },
    "rock": {
        "description": "Crushes your opponents",
        "max-hunger": 1,
        "cost": ["0.1"],
        "favorite-food": "rock"
    }
}
